Makefile
syamaguc/__init__.py
syamaguc/gyazo/__init__.py
syamaguc/gyazo/api.py
syamaguc/gyazo/error.py
syamaguc/gyazo/image.py
syamaguc/gyazo/py.typed
syamaguc/kvs/__init__.py
syamaguc/kvs/kvs.py
syamaguc/scraping/__init__.py
syamaguc/scraping/tor.py
tox.ini
syamaguc-0.3.0.dist-info/LICENSE
syamaguc-0.3.0.dist-info/METADATA
syamaguc-0.3.0.dist-info/WHEEL
syamaguc-0.3.0.dist-info/RECORD
