Metadata-Version: 2.1
Name: syamaguc
Version: 0.3.0
Summary: A Python Project of TEMPLATE
Home-page: https://github.com/syamaguc/python_library_template
License: MIT
Author: syamaguc
Author-email: programmer2844@gmail.com
Requires-Python: >=3.8.1,<4.0.0
Classifier: License :: OSI Approved :: MIT License
Classifier: Programming Language :: Python :: 3
Classifier: Programming Language :: Python :: 3.9
Classifier: Programming Language :: Python :: 3.10
Classifier: Programming Language :: Python :: 3.11
Classifier: Programming Language :: Python :: 3.12
Requires-Dist: dill (>=0.3.7,<0.4.0)
Requires-Dist: python-dateutil (>=2.8.2,<3.0.0)
Requires-Dist: requests (>=2.25.1,<3.0.0)
Requires-Dist: selenium (>=4.15.2,<5.0.0)
Project-URL: Repository, https://github.com/syamaguc/python_library_template
